libraria/__init__.py
libraria/cli.py
libraria/search
libraria/searchpage.html
libraria-0.1.0.dist-info/entry_points.txt
libraria-0.1.0.dist-info/WHEEL
libraria-0.1.0.dist-info/METADATA
libraria-0.1.0.dist-info/RECORD
