Metadata-Version: 2.1
Name: libraria
Version: 0.1.0
Summary: A library for searching libraries for books
Home-page: git@github.com:dang3r/libraria.git
License: MIT
Author: Daniel Cardoza
Author-email: dan@danielcardoza.com
Maintainer: Daniel Cardoza
Maintainer-email: dan@danielcardoza.com
Requires-Python: >=3.6,<4.0
Classifier: License :: OSI Approved :: MIT License
Classifier: Programming Language :: Python :: 3
Classifier: Programming Language :: Python :: 3.6
Classifier: Programming Language :: Python :: 3.7
Classifier: Programming Language :: Python :: 3.8
Requires-Dist: bs4 (>=0.0.1,<0.0.2)
Requires-Dist: click (>=7.0,<8.0)
Requires-Dist: daiquiri (>=2.0.0,<3.0.0)
Requires-Dist: requests (>=2.22.0,<3.0.0)
Project-URL: Repository, git@github.com:dang3r/libraria.git
